tsp_api/__init__.py
tsp_api/__main__.py
tsp_api/api.py
tsp_api/dijkstra.py
tsp_rest_api_server-3.6.dist-info/DESCRIPTION.rst
tsp_rest_api_server-3.6.dist-info/METADATA
tsp_rest_api_server-3.6.dist-info/RECORD
tsp_rest_api_server-3.6.dist-info/WHEEL
tsp_rest_api_server-3.6.dist-info/entry_points.txt
tsp_rest_api_server-3.6.dist-info/metadata.json
tsp_rest_api_server-3.6.dist-info/top_level.txt
tsp_rest_api_server-3.6.dist-info/zip-safe
