Metadata-Version: 2.0
Name: tsp-rest-api-server
Version: 3.6
Summary: TSP Rest Api Server - Rest Api Server using Dijsktra's algorithm applied to travelling salesman problem.
Home-page: https://github.com/caputomarcos/tsp-rest-api-server
Author: Marcos Caputo <caputo.marcos@gmail.com>
Author-email: UNKNOWN
License: MIT
Platform: UNKNOWN
Classifier: Framework :: Flask
Classifier: Programming Language :: Python
Requires-Dist: click (==6.7)
Requires-Dist: Eve (==0.7.4)
Requires-Dist: Events (==0.2.2)
Requires-Dist: flask (<=0.12,>=0.10.1)
Requires-Dist: Flask-PyMongo (==0.5.1)
Requires-Dist: itsdangerous (==0.24)
Requires-Dist: Jinja2 (==2.9.6)
Requires-Dist: MarkupSafe (==0.23)
Requires-Dist: simplejson (==3.11.1)
Requires-Dist: Werkzeug (==0.11.15)
Provides-Extra: dev
Requires-Dist: click (==6.7); extra == 'dev'
Requires-Dist: Eve (==0.7.4); extra == 'dev'
Requires-Dist: Events (==0.2.2); extra == 'dev'
Requires-Dist: flask (<=0.12,>=0.10.1); extra == 'dev'
Requires-Dist: Flask-PyMongo (==0.5.1); extra == 'dev'
Requires-Dist: itsdangerous (==0.24); extra == 'dev'
Requires-Dist: Jinja2 (==2.9.6); extra == 'dev'
Requires-Dist: MarkupSafe (==0.23); extra == 'dev'
Requires-Dist: simplejson (==3.11.1); extra == 'dev'
Requires-Dist: Werkzeug (==0.11.15); extra == 'dev'
Requires-Dist: mock (==2.0.0); extra == 'dev'
Provides-Extra: mongo
Requires-Dist: click (==6.7); extra == 'mongo'
Requires-Dist: Eve (==0.7.4); extra == 'mongo'
Requires-Dist: Events (==0.2.2); extra == 'mongo'
Requires-Dist: flask (<=0.12,>=0.10.1); extra == 'mongo'
Requires-Dist: Flask-PyMongo (==0.5.1); extra == 'mongo'
Requires-Dist: itsdangerous (==0.24); extra == 'mongo'
Requires-Dist: Jinja2 (==2.9.6); extra == 'mongo'
Requires-Dist: MarkupSafe (==0.23); extra == 'mongo'
Requires-Dist: simplejson (==3.11.1); extra == 'mongo'
Requires-Dist: Werkzeug (==0.11.15); extra == 'mongo'
Requires-Dist: pymongo (==3.5.1); extra == 'mongo'
